{"nodes": [{"id": "blog_wp_includes_id3_module_tag_apetag_php", "label": "module.tag.apetag.php", "file_type": "code", "source_file": "blog\\wp-includes\\ID3\\module.tag.apetag.php", "source_location": "L1"}, {"id": "module_tag_apetag_getid3_apetag", "label": "getid3_apetag", "file_type": "code", "source_file": "blog\\wp-includes\\ID3\\module.tag.apetag.php", "source_location": "L21"}, {"id": "module_tag_apetag_getid3_apetag_analyze", "label": ".Analyze()", "file_type": "code", "source_file": "blog\\wp-includes\\ID3\\module.tag.apetag.php", "source_location": "L38"}, {"id": "module_tag_apetag_getid3_apetag_parseapeheaderfooter", "label": ".parseAPEheaderFooter()", "file_type": "code", "source_file": "blog\\wp-includes\\ID3\\module.tag.apetag.php", "source_location": "L359"}, {"id": "module_tag_apetag_getid3_apetag_parseapetagflags", "label": ".parseAPEtagFlags()", "file_type": "code", "source_file": "blog\\wp-includes\\ID3\\module.tag.apetag.php", "source_location": "L389"}, {"id": "module_tag_apetag_getid3_apetag_apecontenttypeflaglookup", "label": ".APEcontentTypeFlagLookup()", "file_type": "code", "source_file": "blog\\wp-includes\\ID3\\module.tag.apetag.php", "source_location": "L410"}, {"id": "module_tag_apetag_getid3_apetag_apetagitemisutf8lookup", "label": ".APEtagItemIsUTF8Lookup()", "file_type": "code", "source_file": "blog\\wp-includes\\ID3\\module.tag.apetag.php", "source_location": "L425"}], "edges": [{"source": "blog_wp_includes_id3_module_tag_apetag_php", "target": "module_tag_apetag_getid3_apetag", "relation": "contains", "confidence": "EXTRACTED", "source_file": "blog\\wp-includes\\ID3\\module.tag.apetag.php", "source_location": "L21", "weight": 1.0}, {"source": "module_tag_apetag_getid3_apetag", "target": "module_tag_apetag_getid3_apetag_analyze", "relation": "method", "confidence": "EXTRACTED", "source_file": "blog\\wp-includes\\ID3\\module.tag.apetag.php", "source_location": "L38", "weight": 1.0}, {"source": "module_tag_apetag_getid3_apetag", "target": "module_tag_apetag_getid3_apetag_parseapeheaderfooter", "relation": "method", "confidence": "EXTRACTED", "source_file": "blog\\wp-includes\\ID3\\module.tag.apetag.php", "source_location": "L359", "weight": 1.0}, {"source": "module_tag_apetag_getid3_apetag", "target": "module_tag_apetag_getid3_apetag_parseapetagflags", "relation": "method", "confidence": "EXTRACTED", "source_file": "blog\\wp-includes\\ID3\\module.tag.apetag.php", "source_location": "L389", "weight": 1.0}, {"source": "module_tag_apetag_getid3_apetag", "target": "module_tag_apetag_getid3_apetag_apecontenttypeflaglookup", "relation": "method", "confidence": "EXTRACTED", "source_file": "blog\\wp-includes\\ID3\\module.tag.apetag.php", "source_location": "L410", "weight": 1.0}, {"source": "module_tag_apetag_getid3_apetag", "target": "module_tag_apetag_getid3_apetag_apetagitemisutf8lookup", "relation": "method", "confidence": "EXTRACTED", "source_file": "blog\\wp-includes\\ID3\\module.tag.apetag.php", "source_location": "L425", "weight": 1.0}, {"source": "module_tag_apetag_getid3_apetag_analyze", "target": "module_tag_apetag_getid3_apetag_parseapeheaderfooter", "relation": "calls", "confidence": "EXTRACTED", "source_file": "blog\\wp-includes\\ID3\\module.tag.apetag.php", "source_location": "L90", "weight": 1.0}, {"source": "module_tag_apetag_getid3_apetag_analyze", "target": "module_tag_apetag_getid3_apetag_parseapetagflags", "relation": "calls", "confidence": "EXTRACTED", "source_file": "blog\\wp-includes\\ID3\\module.tag.apetag.php", "source_location": "L154", "weight": 1.0}, {"source": "module_tag_apetag_getid3_apetag_parseapeheaderfooter", "target": "module_tag_apetag_getid3_apetag_parseapetagflags", "relation": "calls", "confidence": "EXTRACTED", "source_file": "blog\\wp-includes\\ID3\\module.tag.apetag.php", "source_location": "L379", "weight": 1.0}, {"source": "module_tag_apetag_getid3_apetag_parseapetagflags", "target": "module_tag_apetag_getid3_apetag_apecontenttypeflaglookup", "relation": "calls", "confidence": "EXTRACTED", "source_file": "blog\\wp-includes\\ID3\\module.tag.apetag.php", "source_location": "L400", "weight": 1.0}]}