{"nodes": [{"id": "blog_wp_content_plugins_jetpack_jetpack_vendor_automattic_jetpack_videopress_src_class_status_php", "label": "class-status.php", "file_type": "code", "source_file": "blog\\wp-content\\plugins\\jetpack\\jetpack_vendor\\automattic\\jetpack-videopress\\src\\class-status.php", "source_location": "L1"}, {"id": "class_status_status", "label": "Status", "file_type": "code", "source_file": "blog\\wp-content\\plugins\\jetpack\\jetpack_vendor\\automattic\\jetpack-videopress\\src\\class-status.php", "source_location": "L15"}, {"id": "class_status_status_is_active", "label": ".is_active()", "file_type": "code", "source_file": "blog\\wp-content\\plugins\\jetpack\\jetpack_vendor\\automattic\\jetpack-videopress\\src\\class-status.php", "source_location": "L23"}, {"id": "class_status_status_is_jetpack_plugin_active", "label": ".is_jetpack_plugin_active()", "file_type": "code", "source_file": "blog\\wp-content\\plugins\\jetpack\\jetpack_vendor\\automattic\\jetpack-videopress\\src\\class-status.php", "source_location": "L30"}, {"id": "class_status_status_is_jetpack_plugin_and_videopress_module_active", "label": ".is_jetpack_plugin_and_videopress_module_active()", "file_type": "code", "source_file": "blog\\wp-content\\plugins\\jetpack\\jetpack_vendor\\automattic\\jetpack-videopress\\src\\class-status.php", "source_location": "L40"}, {"id": "class_status_status_is_standalone_plugin_active", "label": ".is_standalone_plugin_active()", "file_type": "code", "source_file": "blog\\wp-content\\plugins\\jetpack\\jetpack_vendor\\automattic\\jetpack-videopress\\src\\class-status.php", "source_location": "L49"}, {"id": "class_status_status_is_registrant_plugin_active", "label": ".is_registrant_plugin_active()", "file_type": "code", "source_file": "blog\\wp-content\\plugins\\jetpack\\jetpack_vendor\\automattic\\jetpack-videopress\\src\\class-status.php", "source_location": "L60"}], "edges": [{"source": "blog_wp_content_plugins_jetpack_jetpack_vendor_automattic_jetpack_videopress_src_class_status_php", "target": "jetpack", "relation": "imports", "confidence": "EXTRACTED", "source_file": "blog\\wp-content\\plugins\\jetpack\\jetpack_vendor\\automattic\\jetpack-videopress\\src\\class-status.php", "source_location": "L10", "weight": 1.0}, {"source": "blog_wp_content_plugins_jetpack_jetpack_vendor_automattic_jetpack_videopress_src_class_status_php", "target": "class_status_status", "relation": "contains", "confidence": "EXTRACTED", "source_file": "blog\\wp-content\\plugins\\jetpack\\jetpack_vendor\\automattic\\jetpack-videopress\\src\\class-status.php", "source_location": "L15", "weight": 1.0}, {"source": "class_status_status", "target": "class_status_status_is_active", "relation": "method", "confidence": "EXTRACTED", "source_file": "blog\\wp-content\\plugins\\jetpack\\jetpack_vendor\\automattic\\jetpack-videopress\\src\\class-status.php", "source_location": "L23", "weight": 1.0}, {"source": "class_status_status", "target": "class_status_status_is_jetpack_plugin_active", "relation": "method", "confidence": "EXTRACTED", "source_file": "blog\\wp-content\\plugins\\jetpack\\jetpack_vendor\\automattic\\jetpack-videopress\\src\\class-status.php", "source_location": "L30", "weight": 1.0}, {"source": "class_status_status", "target": "class_status_status_is_jetpack_plugin_and_videopress_module_active", "relation": "method", "confidence": "EXTRACTED", "source_file": "blog\\wp-content\\plugins\\jetpack\\jetpack_vendor\\automattic\\jetpack-videopress\\src\\class-status.php", "source_location": "L40", "weight": 1.0}, {"source": "class_status_status", "target": "class_status_status_is_standalone_plugin_active", "relation": "method", "confidence": "EXTRACTED", "source_file": "blog\\wp-content\\plugins\\jetpack\\jetpack_vendor\\automattic\\jetpack-videopress\\src\\class-status.php", "source_location": "L49", "weight": 1.0}, {"source": "class_status_status", "target": "class_status_status_is_registrant_plugin_active", "relation": "method", "confidence": "EXTRACTED", "source_file": "blog\\wp-content\\plugins\\jetpack\\jetpack_vendor\\automattic\\jetpack-videopress\\src\\class-status.php", "source_location": "L60", "weight": 1.0}]}