{"nodes": [{"id": "blog_wp_content_plugins_jetpack_modules_widgets_simple_payments_php", "label": "simple-payments.php", "file_type": "code", "source_file": "blog\\wp-content\\plugins\\jetpack\\modules\\widgets\\simple-payments.php", "source_location": "L1"}, {"id": "simple_payments_jetpack_simple_payments_widget", "label": "Jetpack_Simple_Payments_Widget", "file_type": "code", "source_file": "blog\\wp-content\\plugins\\jetpack\\modules\\widgets\\simple-payments.php", "source_location": "L18"}, {"id": "simple_payments_jetpack_simple_payments_widget_construct", "label": ".__construct()", "file_type": "code", "source_file": "blog\\wp-content\\plugins\\jetpack\\modules\\widgets\\simple-payments.php", "source_location": "L64"}, {"id": "simple_payments_jetpack_simple_payments_widget_hide_simple_payment_widget", "label": ".hide_simple_payment_widget()", "file_type": "code", "source_file": "blog\\wp-content\\plugins\\jetpack\\modules\\widgets\\simple-payments.php", "source_location": "L102"}, {"id": "simple_payments_jetpack_simple_payments_widget_defaults", "label": ".defaults()", "file_type": "code", "source_file": "blog\\wp-content\\plugins\\jetpack\\modules\\widgets\\simple-payments.php", "source_location": "L114"}, {"id": "simple_payments_jetpack_simple_payments_widget_filter_nonces", "label": ".filter_nonces()", "file_type": "code", "source_file": "blog\\wp-content\\plugins\\jetpack\\modules\\widgets\\simple-payments.php", "source_location": "L140"}, {"id": "simple_payments_jetpack_simple_payments_widget_enqueue_style", "label": ".enqueue_style()", "file_type": "code", "source_file": "blog\\wp-content\\plugins\\jetpack\\modules\\widgets\\simple-payments.php", "source_location": "L148"}, {"id": "simple_payments_jetpack_simple_payments_widget_admin_enqueue_styles", "label": ".admin_enqueue_styles()", "file_type": "code", "source_file": "blog\\wp-content\\plugins\\jetpack\\modules\\widgets\\simple-payments.php", "source_location": "L155"}, {"id": "simple_payments_jetpack_simple_payments_widget_admin_enqueue_scripts", "label": ".admin_enqueue_scripts()", "file_type": "code", "source_file": "blog\\wp-content\\plugins\\jetpack\\modules\\widgets\\simple-payments.php", "source_location": "L167"}, {"id": "simple_payments_jetpack_simple_payments_widget_ajax_get_payment_buttons", "label": ".ajax_get_payment_buttons()", "file_type": "code", "source_file": "blog\\wp-content\\plugins\\jetpack\\modules\\widgets\\simple-payments.php", "source_location": "L188"}, {"id": "simple_payments_jetpack_simple_payments_widget_format_product_post_for_ajax_reponse", "label": ".format_product_post_for_ajax_reponse()", "file_type": "code", "source_file": "blog\\wp-content\\plugins\\jetpack\\modules\\widgets\\simple-payments.php", "source_location": "L221"}, {"id": "simple_payments_jetpack_simple_payments_widget_ajax_save_payment_button", "label": ".ajax_save_payment_button()", "file_type": "code", "source_file": "blog\\wp-content\\plugins\\jetpack\\modules\\widgets\\simple-payments.php", "source_location": "L231"}, {"id": "simple_payments_jetpack_simple_payments_widget_ajax_delete_payment_button", "label": ".ajax_delete_payment_button()", "file_type": "code", "source_file": "blog\\wp-content\\plugins\\jetpack\\modules\\widgets\\simple-payments.php", "source_location": "L304"}, {"id": "simple_payments_jetpack_simple_payments_widget_get_decimal_places", "label": ".get_decimal_places()", "file_type": "code", "source_file": "blog\\wp-content\\plugins\\jetpack\\modules\\widgets\\simple-payments.php", "source_location": "L345"}, {"id": "simple_payments_jetpack_simple_payments_widget_validate_ajax_params", "label": ".validate_ajax_params()", "file_type": "code", "source_file": "blog\\wp-content\\plugins\\jetpack\\modules\\widgets\\simple-payments.php", "source_location": "L359"}, {"id": "simple_payments_jetpack_simple_payments_widget_get_first_product_id", "label": ".get_first_product_id()", "file_type": "code", "source_file": "blog\\wp-content\\plugins\\jetpack\\modules\\widgets\\simple-payments.php", "source_location": "L392"}, {"id": "simple_payments_jetpack_simple_payments_widget_widget", "label": ".widget()", "file_type": "code", "source_file": "blog\\wp-content\\plugins\\jetpack\\modules\\widgets\\simple-payments.php", "source_location": "L415"}, {"id": "simple_payments_jetpack_simple_payments_widget_get_latest_field_value", "label": ".get_latest_field_value()", "file_type": "code", "source_file": "blog\\wp-content\\plugins\\jetpack\\modules\\widgets\\simple-payments.php", "source_location": "L461"}, {"id": "simple_payments_jetpack_simple_payments_widget_get_product_from_post", "label": ".get_product_from_post()", "file_type": "code", "source_file": "blog\\wp-content\\plugins\\jetpack\\modules\\widgets\\simple-payments.php", "source_location": "L474"}, {"id": "simple_payments_jetpack_simple_payments_widget_record_event", "label": ".record_event()", "file_type": "code", "source_file": "blog\\wp-content\\plugins\\jetpack\\modules\\widgets\\simple-payments.php", "source_location": "L503"}, {"id": "simple_payments_jetpack_simple_payments_widget_update", "label": ".update()", "file_type": "code", "source_file": "blog\\wp-content\\plugins\\jetpack\\modules\\widgets\\simple-payments.php", "source_location": "L533"}, {"id": "simple_payments_jetpack_simple_payments_widget_form", "label": ".form()", "file_type": "code", "source_file": "blog\\wp-content\\plugins\\jetpack\\modules\\widgets\\simple-payments.php", "source_location": "L587"}, {"id": "simple_payments_register_widget_jetpack_simple_payments", "label": "register_widget_jetpack_simple_payments()", "file_type": "code", "source_file": "blog\\wp-content\\plugins\\jetpack\\modules\\widgets\\simple-payments.php", "source_location": "L615"}], "edges": [{"source": "blog_wp_content_plugins_jetpack_modules_widgets_simple_payments_php", "target": "tracking", "relation": "imports", "confidence": "EXTRACTED", "source_file": "blog\\wp-content\\plugins\\jetpack\\modules\\widgets\\simple-payments.php", "source_location": "L5", "weight": 1.0}, {"source": "blog_wp_content_plugins_jetpack_modules_widgets_simple_payments_php", "target": "simple_payments_jetpack_simple_payments_widget", "relation": "contains", "confidence": "EXTRACTED", "source_file": "blog\\wp-content\\plugins\\jetpack\\modules\\widgets\\simple-payments.php", "source_location": "L18", "weight": 1.0}, {"source": "simple_payments_jetpack_simple_payments_widget", "target": "simple_payments_jetpack_simple_payments_widget_construct", "relation": "method", "confidence": "EXTRACTED", "source_file": "blog\\wp-content\\plugins\\jetpack\\modules\\widgets\\simple-payments.php", "source_location": "L64", "weight": 1.0}, {"source": "simple_payments_jetpack_simple_payments_widget", "target": "simple_payments_jetpack_simple_payments_widget_hide_simple_payment_widget", "relation": "method", "confidence": "EXTRACTED", "source_file": "blog\\wp-content\\plugins\\jetpack\\modules\\widgets\\simple-payments.php", "source_location": "L102", "weight": 1.0}, {"source": "simple_payments_jetpack_simple_payments_widget", "target": "simple_payments_jetpack_simple_payments_widget_defaults", "relation": "method", "confidence": "EXTRACTED", "source_file": "blog\\wp-content\\plugins\\jetpack\\modules\\widgets\\simple-payments.php", "source_location": "L114", "weight": 1.0}, {"source": "simple_payments_jetpack_simple_payments_widget", "target": "simple_payments_jetpack_simple_payments_widget_filter_nonces", "relation": "method", "confidence": "EXTRACTED", "source_file": "blog\\wp-content\\plugins\\jetpack\\modules\\widgets\\simple-payments.php", "source_location": "L140", "weight": 1.0}, {"source": "simple_payments_jetpack_simple_payments_widget", "target": "simple_payments_jetpack_simple_payments_widget_enqueue_style", "relation": "method", "confidence": "EXTRACTED", "source_file": "blog\\wp-content\\plugins\\jetpack\\modules\\widgets\\simple-payments.php", "source_location": "L148", "weight": 1.0}, {"source": "simple_payments_jetpack_simple_payments_widget", "target": "simple_payments_jetpack_simple_payments_widget_admin_enqueue_styles", "relation": "method", "confidence": "EXTRACTED", "source_file": "blog\\wp-content\\plugins\\jetpack\\modules\\widgets\\simple-payments.php", "source_location": "L155", "weight": 1.0}, {"source": "simple_payments_jetpack_simple_payments_widget", "target": "simple_payments_jetpack_simple_payments_widget_admin_enqueue_scripts", "relation": "method", "confidence": "EXTRACTED", "source_file": "blog\\wp-content\\plugins\\jetpack\\modules\\widgets\\simple-payments.php", "source_location": "L167", "weight": 1.0}, {"source": "simple_payments_jetpack_simple_payments_widget", "target": "simple_payments_jetpack_simple_payments_widget_ajax_get_payment_buttons", "relation": "method", "confidence": "EXTRACTED", "source_file": "blog\\wp-content\\plugins\\jetpack\\modules\\widgets\\simple-payments.php", "source_location": "L188", "weight": 1.0}, {"source": "simple_payments_jetpack_simple_payments_widget", "target": "simple_payments_jetpack_simple_payments_widget_format_product_post_for_ajax_reponse", "relation": "method", "confidence": "EXTRACTED", "source_file": "blog\\wp-content\\plugins\\jetpack\\modules\\widgets\\simple-payments.php", "source_location": "L221", "weight": 1.0}, {"source": "simple_payments_jetpack_simple_payments_widget", "target": "simple_payments_jetpack_simple_payments_widget_ajax_save_payment_button", "relation": "method", "confidence": "EXTRACTED", "source_file": "blog\\wp-content\\plugins\\jetpack\\modules\\widgets\\simple-payments.php", "source_location": "L231", "weight": 1.0}, {"source": "simple_payments_jetpack_simple_payments_widget", "target": "simple_payments_jetpack_simple_payments_widget_ajax_delete_payment_button", "relation": "method", "confidence": "EXTRACTED", "source_file": "blog\\wp-content\\plugins\\jetpack\\modules\\widgets\\simple-payments.php", "source_location": "L304", "weight": 1.0}, {"source": "simple_payments_jetpack_simple_payments_widget", "target": "simple_payments_jetpack_simple_payments_widget_get_decimal_places", "relation": "method", "confidence": "EXTRACTED", "source_file": "blog\\wp-content\\plugins\\jetpack\\modules\\widgets\\simple-payments.php", "source_location": "L345", "weight": 1.0}, {"source": "simple_payments_jetpack_simple_payments_widget", "target": "simple_payments_jetpack_simple_payments_widget_validate_ajax_params", "relation": "method", "confidence": "EXTRACTED", "source_file": "blog\\wp-content\\plugins\\jetpack\\modules\\widgets\\simple-payments.php", "source_location": "L359", "weight": 1.0}, {"source": "simple_payments_jetpack_simple_payments_widget", "target": "simple_payments_jetpack_simple_payments_widget_get_first_product_id", "relation": "method", "confidence": "EXTRACTED", "source_file": "blog\\wp-content\\plugins\\jetpack\\modules\\widgets\\simple-payments.php", "source_location": "L392", "weight": 1.0}, {"source": "simple_payments_jetpack_simple_payments_widget", "target": "simple_payments_jetpack_simple_payments_widget_widget", "relation": "method", "confidence": "EXTRACTED", "source_file": "blog\\wp-content\\plugins\\jetpack\\modules\\widgets\\simple-payments.php", "source_location": "L415", "weight": 1.0}, {"source": "simple_payments_jetpack_simple_payments_widget", "target": "simple_payments_jetpack_simple_payments_widget_get_latest_field_value", "relation": "method", "confidence": "EXTRACTED", "source_file": "blog\\wp-content\\plugins\\jetpack\\modules\\widgets\\simple-payments.php", "source_location": "L461", "weight": 1.0}, {"source": "simple_payments_jetpack_simple_payments_widget", "target": "simple_payments_jetpack_simple_payments_widget_get_product_from_post", "relation": "method", "confidence": "EXTRACTED", "source_file": "blog\\wp-content\\plugins\\jetpack\\modules\\widgets\\simple-payments.php", "source_location": "L474", "weight": 1.0}, {"source": "simple_payments_jetpack_simple_payments_widget", "target": "simple_payments_jetpack_simple_payments_widget_record_event", "relation": "method", "confidence": "EXTRACTED", "source_file": "blog\\wp-content\\plugins\\jetpack\\modules\\widgets\\simple-payments.php", "source_location": "L503", "weight": 1.0}, {"source": "simple_payments_jetpack_simple_payments_widget", "target": "simple_payments_jetpack_simple_payments_widget_update", "relation": "method", "confidence": "EXTRACTED", "source_file": "blog\\wp-content\\plugins\\jetpack\\modules\\widgets\\simple-payments.php", "source_location": "L533", "weight": 1.0}, {"source": "simple_payments_jetpack_simple_payments_widget", "target": "simple_payments_jetpack_simple_payments_widget_form", "relation": "method", "confidence": "EXTRACTED", "source_file": "blog\\wp-content\\plugins\\jetpack\\modules\\widgets\\simple-payments.php", "source_location": "L587", "weight": 1.0}, {"source": "blog_wp_content_plugins_jetpack_modules_widgets_simple_payments_php", "target": "simple_payments_register_widget_jetpack_simple_payments", "relation": "contains", "confidence": "EXTRACTED", "source_file": "blog\\wp-content\\plugins\\jetpack\\modules\\widgets\\simple-payments.php", "source_location": "L615", "weight": 1.0}, {"source": "simple_payments_jetpack_simple_payments_widget_defaults", "target": "simple_payments_jetpack_simple_payments_widget_get_first_product_id", "relation": "calls", "confidence": "EXTRACTED", "source_file": "blog\\wp-content\\plugins\\jetpack\\modules\\widgets\\simple-payments.php", "source_location": "L116", "weight": 1.0}, {"source": "simple_payments_jetpack_simple_payments_widget_ajax_save_payment_button", "target": "simple_payments_jetpack_simple_payments_widget_validate_ajax_params", "relation": "calls", "confidence": "EXTRACTED", "source_file": "blog\\wp-content\\plugins\\jetpack\\modules\\widgets\\simple-payments.php", "source_location": "L250", "weight": 1.0}, {"source": "simple_payments_jetpack_simple_payments_widget_ajax_save_payment_button", "target": "simple_payments_jetpack_simple_payments_widget_record_event", "relation": "calls", "confidence": "EXTRACTED", "source_file": "blog\\wp-content\\plugins\\jetpack\\modules\\widgets\\simple-payments.php", "source_location": "L288", "weight": 1.0}, {"source": "simple_payments_jetpack_simple_payments_widget_ajax_delete_payment_button", "target": "simple_payments_jetpack_simple_payments_widget_record_event", "relation": "calls", "confidence": "EXTRACTED", "source_file": "blog\\wp-content\\plugins\\jetpack\\modules\\widgets\\simple-payments.php", "source_location": "L334", "weight": 1.0}, {"source": "simple_payments_jetpack_simple_payments_widget_validate_ajax_params", "target": "simple_payments_jetpack_simple_payments_widget_get_decimal_places", "relation": "calls", "confidence": "EXTRACTED", "source_file": "blog\\wp-content\\plugins\\jetpack\\modules\\widgets\\simple-payments.php", "source_location": "L377", "weight": 1.0}, {"source": "simple_payments_jetpack_simple_payments_widget_widget", "target": "simple_payments_jetpack_simple_payments_widget_defaults", "relation": "calls", "confidence": "EXTRACTED", "source_file": "blog\\wp-content\\plugins\\jetpack\\modules\\widgets\\simple-payments.php", "source_location": "L416", "weight": 1.0}, {"source": "simple_payments_jetpack_simple_payments_widget_widget", "target": "simple_payments_jetpack_simple_payments_widget_enqueue_style", "relation": "calls", "confidence": "EXTRACTED", "source_file": "blog\\wp-content\\plugins\\jetpack\\modules\\widgets\\simple-payments.php", "source_location": "L419", "weight": 1.0}, {"source": "simple_payments_jetpack_simple_payments_widget_get_product_from_post", "target": "simple_payments_jetpack_simple_payments_widget_defaults", "relation": "calls", "confidence": "EXTRACTED", "source_file": "blog\\wp-content\\plugins\\jetpack\\modules\\widgets\\simple-payments.php", "source_location": "L493", "weight": 1.0}, {"source": "simple_payments_jetpack_simple_payments_widget_update", "target": "simple_payments_jetpack_simple_payments_widget_defaults", "relation": "calls", "confidence": "EXTRACTED", "source_file": "blog\\wp-content\\plugins\\jetpack\\modules\\widgets\\simple-payments.php", "source_location": "L534", "weight": 1.0}, {"source": "simple_payments_jetpack_simple_payments_widget_update", "target": "simple_payments_jetpack_simple_payments_widget_get_latest_field_value", "relation": "calls", "confidence": "EXTRACTED", "source_file": "blog\\wp-content\\plugins\\jetpack\\modules\\widgets\\simple-payments.php", "source_location": "L540", "weight": 1.0}, {"source": "simple_payments_jetpack_simple_payments_widget_update", "target": "simple_payments_jetpack_simple_payments_widget_get_product_from_post", "relation": "calls", "confidence": "EXTRACTED", "source_file": "blog\\wp-content\\plugins\\jetpack\\modules\\widgets\\simple-payments.php", "source_location": "L547", "weight": 1.0}, {"source": "simple_payments_jetpack_simple_payments_widget_form", "target": "simple_payments_jetpack_simple_payments_widget_defaults", "relation": "calls", "confidence": "EXTRACTED", "source_file": "blog\\wp-content\\plugins\\jetpack\\modules\\widgets\\simple-payments.php", "source_location": "L597", "weight": 1.0}]}