{"nodes": [{"id": "blog_wp_content_plugins_wpforms_lite_includes_deprecated_php", "label": "deprecated.php", "file_type": "code", "source_file": "blog\\wp-content\\plugins\\wpforms-lite\\includes\\deprecated.php", "source_location": "L1"}, {"id": "deprecated_removed", "label": "Removed", "file_type": "code", "source_file": "blog\\wp-content\\plugins\\wpforms-lite\\includes\\deprecated.php", "source_location": "L13"}, {"id": "deprecated_removed_construct", "label": ".__construct()", "file_type": "code", "source_file": "blog\\wp-content\\plugins\\wpforms-lite\\includes\\deprecated.php", "source_location": "L30"}, {"id": "deprecated_removed_get", "label": ".__get()", "file_type": "code", "source_file": "blog\\wp-content\\plugins\\wpforms-lite\\includes\\deprecated.php", "source_location": "L42"}, {"id": "deprecated_removed_set", "label": ".__set()", "file_type": "code", "source_file": "blog\\wp-content\\plugins\\wpforms-lite\\includes\\deprecated.php", "source_location": "L55"}, {"id": "deprecated_removed_isset", "label": ".__isset()", "file_type": "code", "source_file": "blog\\wp-content\\plugins\\wpforms-lite\\includes\\deprecated.php", "source_location": "L67"}, {"id": "deprecated_removed_call", "label": ".__call()", "file_type": "code", "source_file": "blog\\wp-content\\plugins\\wpforms-lite\\includes\\deprecated.php", "source_location": "L81"}, {"id": "deprecated_removed_callstatic", "label": ".__callStatic()", "file_type": "code", "source_file": "blog\\wp-content\\plugins\\wpforms-lite\\includes\\deprecated.php", "source_location": "L94"}, {"id": "deprecated_removed_trigger_error", "label": ".trigger_error()", "file_type": "code", "source_file": "blog\\wp-content\\plugins\\wpforms-lite\\includes\\deprecated.php", "source_location": "L106"}, {"id": "deprecated_loader", "label": "Loader", "file_type": "code", "source_file": "blog\\wp-content\\plugins\\wpforms-lite\\includes\\deprecated.php", "source_location": "L133"}, {"id": "deprecated_wpforms_builder_notification_get_state", "label": "wpforms_builder_notification_get_state()", "file_type": "code", "source_file": "blog\\wp-content\\plugins\\wpforms-lite\\includes\\deprecated.php", "source_location": "L371"}, {"id": "deprecated_wpforms_size_to_megabytes", "label": "wpforms_size_to_megabytes()", "file_type": "code", "source_file": "blog\\wp-content\\plugins\\wpforms-lite\\includes\\deprecated.php", "source_location": "L388"}, {"id": "deprecated_defaultscreen", "label": "DefaultScreen", "file_type": "code", "source_file": "blog\\wp-content\\plugins\\wpforms-lite\\includes\\deprecated.php", "source_location": "L405"}], "edges": [{"source": "blog_wp_content_plugins_wpforms_lite_includes_deprecated_php", "target": "deprecated_removed", "relation": "contains", "confidence": "EXTRACTED", "source_file": "blog\\wp-content\\plugins\\wpforms-lite\\includes\\deprecated.php", "source_location": "L13", "weight": 1.0}, {"source": "deprecated_removed", "target": "deprecated_removed_construct", "relation": "method", "confidence": "EXTRACTED", "source_file": "blog\\wp-content\\plugins\\wpforms-lite\\includes\\deprecated.php", "source_location": "L30", "weight": 1.0}, {"source": "deprecated_removed", "target": "deprecated_removed_get", "relation": "method", "confidence": "EXTRACTED", "source_file": "blog\\wp-content\\plugins\\wpforms-lite\\includes\\deprecated.php", "source_location": "L42", "weight": 1.0}, {"source": "deprecated_removed", "target": "deprecated_removed_set", "relation": "method", "confidence": "EXTRACTED", "source_file": "blog\\wp-content\\plugins\\wpforms-lite\\includes\\deprecated.php", "source_location": "L55", "weight": 1.0}, {"source": "deprecated_removed", "target": "deprecated_removed_isset", "relation": "method", "confidence": "EXTRACTED", "source_file": "blog\\wp-content\\plugins\\wpforms-lite\\includes\\deprecated.php", "source_location": "L67", "weight": 1.0}, {"source": "deprecated_removed", "target": "deprecated_removed_call", "relation": "method", "confidence": "EXTRACTED", "source_file": "blog\\wp-content\\plugins\\wpforms-lite\\includes\\deprecated.php", "source_location": "L81", "weight": 1.0}, {"source": "deprecated_removed", "target": "deprecated_removed_callstatic", "relation": "method", "confidence": "EXTRACTED", "source_file": "blog\\wp-content\\plugins\\wpforms-lite\\includes\\deprecated.php", "source_location": "L94", "weight": 1.0}, {"source": "deprecated_removed", "target": "deprecated_removed_trigger_error", "relation": "method", "confidence": "EXTRACTED", "source_file": "blog\\wp-content\\plugins\\wpforms-lite\\includes\\deprecated.php", "source_location": "L106", "weight": 1.0}, {"source": "blog_wp_content_plugins_wpforms_lite_includes_deprecated_php", "target": "removed", "relation": "imports", "confidence": "EXTRACTED", "source_file": "blog\\wp-content\\plugins\\wpforms-lite\\includes\\deprecated.php", "source_location": "L131", "weight": 1.0}, {"source": "blog_wp_content_plugins_wpforms_lite_includes_deprecated_php", "target": "deprecated_loader", "relation": "contains", "confidence": "EXTRACTED", "source_file": "blog\\wp-content\\plugins\\wpforms-lite\\includes\\deprecated.php", "source_location": "L133", "weight": 1.0}, {"source": "blog_wp_content_plugins_wpforms_lite_includes_deprecated_php", "target": "deprecated_wpforms_builder_notification_get_state", "relation": "contains", "confidence": "EXTRACTED", "source_file": "blog\\wp-content\\plugins\\wpforms-lite\\includes\\deprecated.php", "source_location": "L371", "weight": 1.0}, {"source": "blog_wp_content_plugins_wpforms_lite_includes_deprecated_php", "target": "deprecated_wpforms_size_to_megabytes", "relation": "contains", "confidence": "EXTRACTED", "source_file": "blog\\wp-content\\plugins\\wpforms-lite\\includes\\deprecated.php", "source_location": "L388", "weight": 1.0}, {"source": "blog_wp_content_plugins_wpforms_lite_includes_deprecated_php", "target": "deprecated_defaultscreen", "relation": "contains", "confidence": "EXTRACTED", "source_file": "blog\\wp-content\\plugins\\wpforms-lite\\includes\\deprecated.php", "source_location": "L405", "weight": 1.0}]}