{"nodes": [{"id": "blog_wp_includes_js_jquery_jquery_color_min_js", "label": "jquery.color.min.js", "file_type": "code", "source_file": "blog\\wp-includes\\js\\jquery\\jquery.color.min.js", "source_location": "L1"}, {"id": "jquery_color_min_b", "label": "b()", "file_type": "code", "source_file": "blog\\wp-includes\\js\\jquery\\jquery.color.min.js", "source_location": "L2"}, {"id": "jquery_color_min_g", "label": "g()", "file_type": "code", "source_file": "blog\\wp-includes\\js\\jquery\\jquery.color.min.js", "source_location": "L2"}, {"id": "jquery_color_min_m", "label": "m()", "file_type": "code", "source_file": "blog\\wp-includes\\js\\jquery\\jquery.color.min.js", "source_location": "L2"}, {"id": "jquery_color_min_o", "label": "o()", "file_type": "code", "source_file": "blog\\wp-includes\\js\\jquery\\jquery.color.min.js", "source_location": "L2"}], "edges": [{"source": "blog_wp_includes_js_jquery_jquery_color_min_js", "target": "jquery_color_min_b", "relation": "contains", "confidence": "EXTRACTED", "source_file": "blog\\wp-includes\\js\\jquery\\jquery.color.min.js", "source_location": "L2", "weight": 1.0}, {"source": "blog_wp_includes_js_jquery_jquery_color_min_js", "target": "jquery_color_min_g", "relation": "contains", "confidence": "EXTRACTED", "source_file": "blog\\wp-includes\\js\\jquery\\jquery.color.min.js", "source_location": "L2", "weight": 1.0}, {"source": "blog_wp_includes_js_jquery_jquery_color_min_js", "target": "jquery_color_min_m", "relation": "contains", "confidence": "EXTRACTED", "source_file": "blog\\wp-includes\\js\\jquery\\jquery.color.min.js", "source_location": "L2", "weight": 1.0}, {"source": "blog_wp_includes_js_jquery_jquery_color_min_js", "target": "jquery_color_min_o", "relation": "contains", "confidence": "EXTRACTED", "source_file": "blog\\wp-includes\\js\\jquery\\jquery.color.min.js", "source_location": "L2", "weight": 1.0}]}