{"nodes": [{"id": "blog_wp_content_plugins_bluehost_wordpress_plugin_vendor_typesense_typesense_php_src_apicall_php", "label": "ApiCall.php", "file_type": "code", "source_file": "blog\\wp-content\\plugins\\bluehost-wordpress-plugin\\vendor\\typesense\\typesense-php\\src\\ApiCall.php", "source_location": "L1"}, {"id": "apicall_apicall", "label": "ApiCall", "file_type": "code", "source_file": "blog\\wp-content\\plugins\\bluehost-wordpress-plugin\\vendor\\typesense\\typesense-php\\src\\ApiCall.php", "source_location": "L27"}, {"id": "apicall_apicall_construct", "label": ".__construct()", "file_type": "code", "source_file": "blog\\wp-content\\plugins\\bluehost-wordpress-plugin\\vendor\\typesense\\typesense-php\\src\\ApiCall.php", "source_location": "L62"}, {"id": "apicall_apicall_initializenodes", "label": ".initializeNodes()", "file_type": "code", "source_file": "blog\\wp-content\\plugins\\bluehost-wordpress-plugin\\vendor\\typesense\\typesense-php\\src\\ApiCall.php", "source_location": "L75"}, {"id": "apicall_apicall_get", "label": ".get()", "file_type": "code", "source_file": "blog\\wp-content\\plugins\\bluehost-wordpress-plugin\\vendor\\typesense\\typesense-php\\src\\ApiCall.php", "source_location": "L95"}, {"id": "apicall_apicall_post", "label": ".post()", "file_type": "code", "source_file": "blog\\wp-content\\plugins\\bluehost-wordpress-plugin\\vendor\\typesense\\typesense-php\\src\\ApiCall.php", "source_location": "L112"}, {"id": "apicall_apicall_put", "label": ".put()", "file_type": "code", "source_file": "blog\\wp-content\\plugins\\bluehost-wordpress-plugin\\vendor\\typesense\\typesense-php\\src\\ApiCall.php", "source_location": "L126"}, {"id": "apicall_apicall_delete", "label": ".delete()", "file_type": "code", "source_file": "blog\\wp-content\\plugins\\bluehost-wordpress-plugin\\vendor\\typesense\\typesense-php\\src\\ApiCall.php", "source_location": "L139"}, {"id": "apicall_apicall_makerequest", "label": ".makeRequest()", "file_type": "code", "source_file": "blog\\wp-content\\plugins\\bluehost-wordpress-plugin\\vendor\\typesense\\typesense-php\\src\\ApiCall.php", "source_location": "L156"}, {"id": "apicall_apicall_getrequestoptions", "label": ".getRequestOptions()", "file_type": "code", "source_file": "blog\\wp-content\\plugins\\bluehost-wordpress-plugin\\vendor\\typesense\\typesense-php\\src\\ApiCall.php", "source_location": "L226"}, {"id": "apicall_apicall_nodedueforhealthcheck", "label": ".nodeDueForHealthCheck()", "file_type": "code", "source_file": "blog\\wp-content\\plugins\\bluehost-wordpress-plugin\\vendor\\typesense\\typesense-php\\src\\ApiCall.php", "source_location": "L241"}, {"id": "apicall_apicall_setnodehealthcheck", "label": ".setNodeHealthcheck()", "file_type": "code", "source_file": "blog\\wp-content\\plugins\\bluehost-wordpress-plugin\\vendor\\typesense\\typesense-php\\src\\ApiCall.php", "source_location": "L256"}, {"id": "apicall_apicall_getnode", "label": ".getNode()", "file_type": "code", "source_file": "blog\\wp-content\\plugins\\bluehost-wordpress-plugin\\vendor\\typesense\\typesense-php\\src\\ApiCall.php", "source_location": "L268"}, {"id": "apicall_apicall_getexception", "label": ".getException()", "file_type": "code", "source_file": "blog\\wp-content\\plugins\\bluehost-wordpress-plugin\\vendor\\typesense\\typesense-php\\src\\ApiCall.php", "source_location": "L297"}], "edges": [{"source": "blog_wp_content_plugins_bluehost_wordpress_plugin_vendor_typesense_typesense_php_src_apicall_php", "target": "node", "relation": "imports", "confidence": "EXTRACTED", "source_file": "blog\\wp-content\\plugins\\bluehost-wordpress-plugin\\vendor\\typesense\\typesense-php\\src\\ApiCall.php", "source_location": "L5", "weight": 1.0}, {"source": "blog_wp_content_plugins_bluehost_wordpress_plugin_vendor_typesense_typesense_php_src_apicall_php", "target": "guzzleexception", "relation": "imports", "confidence": "EXTRACTED", "source_file": "blog\\wp-content\\plugins\\bluehost-wordpress-plugin\\vendor\\typesense\\typesense-php\\src\\ApiCall.php", "source_location": "L6", "weight": 1.0}, {"source": "blog_wp_content_plugins_bluehost_wordpress_plugin_vendor_typesense_typesense_php_src_apicall_php", "target": "configuration", "relation": "imports", "confidence": "EXTRACTED", "source_file": "blog\\wp-content\\plugins\\bluehost-wordpress-plugin\\vendor\\typesense\\typesense-php\\src\\ApiCall.php", "source_location": "L7", "weight": 1.0}, {"source": "blog_wp_content_plugins_bluehost_wordpress_plugin_vendor_typesense_typesense_php_src_apicall_php", "target": "clientexception", "relation": "imports", "confidence": "EXTRACTED", "source_file": "blog\\wp-content\\plugins\\bluehost-wordpress-plugin\\vendor\\typesense\\typesense-php\\src\\ApiCall.php", "source_location": "L8", "weight": 1.0}, {"source": "blog_wp_content_plugins_bluehost_wordpress_plugin_vendor_typesense_typesense_php_src_apicall_php", "target": "requestexception", "relation": "imports", "confidence": "EXTRACTED", "source_file": "blog\\wp-content\\plugins\\bluehost-wordpress-plugin\\vendor\\typesense\\typesense-php\\src\\ApiCall.php", "source_location": "L9", "weight": 1.0}, {"source": "blog_wp_content_plugins_bluehost_wordpress_plugin_vendor_typesense_typesense_php_src_apicall_php", "target": "servererror", "relation": "imports", "confidence": "EXTRACTED", "source_file": "blog\\wp-content\\plugins\\bluehost-wordpress-plugin\\vendor\\typesense\\typesense-php\\src\\ApiCall.php", "source_location": "L10", "weight": 1.0}, {"source": "blog_wp_content_plugins_bluehost_wordpress_plugin_vendor_typesense_typesense_php_src_apicall_php", "target": "objectnotfound", "relation": "imports", "confidence": "EXTRACTED", "source_file": "blog\\wp-content\\plugins\\bluehost-wordpress-plugin\\vendor\\typesense\\typesense-php\\src\\ApiCall.php", "source_location": "L11", "weight": 1.0}, {"source": "blog_wp_content_plugins_bluehost_wordpress_plugin_vendor_typesense_typesense_php_src_apicall_php", "target": "requestmalformed", "relation": "imports", "confidence": "EXTRACTED", "source_file": "blog\\wp-content\\plugins\\bluehost-wordpress-plugin\\vendor\\typesense\\typesense-php\\src\\ApiCall.php", "source_location": "L12", "weight": 1.0}, {"source": "blog_wp_content_plugins_bluehost_wordpress_plugin_vendor_typesense_typesense_php_src_apicall_php", "target": "httpstatus0error", "relation": "imports", "confidence": "EXTRACTED", "source_file": "blog\\wp-content\\plugins\\bluehost-wordpress-plugin\\vendor\\typesense\\typesense-php\\src\\ApiCall.php", "source_location": "L13", "weight": 1.0}, {"source": "blog_wp_content_plugins_bluehost_wordpress_plugin_vendor_typesense_typesense_php_src_apicall_php", "target": "serviceunavailable", "relation": "imports", "confidence": "EXTRACTED", "source_file": "blog\\wp-content\\plugins\\bluehost-wordpress-plugin\\vendor\\typesense\\typesense-php\\src\\ApiCall.php", "source_location": "L14", "weight": 1.0}, {"source": "blog_wp_content_plugins_bluehost_wordpress_plugin_vendor_typesense_typesense_php_src_apicall_php", "target": "requestunauthorized", "relation": "imports", "confidence": "EXTRACTED", "source_file": "blog\\wp-content\\plugins\\bluehost-wordpress-plugin\\vendor\\typesense\\typesense-php\\src\\ApiCall.php", "source_location": "L15", "weight": 1.0}, {"source": "blog_wp_content_plugins_bluehost_wordpress_plugin_vendor_typesense_typesense_php_src_apicall_php", "target": "objectalreadyexists", "relation": "imports", "confidence": "EXTRACTED", "source_file": "blog\\wp-content\\plugins\\bluehost-wordpress-plugin\\vendor\\typesense\\typesense-php\\src\\ApiCall.php", "source_location": "L16", "weight": 1.0}, {"source": "blog_wp_content_plugins_bluehost_wordpress_plugin_vendor_typesense_typesense_php_src_apicall_php", "target": "objectunprocessable", "relation": "imports", "confidence": "EXTRACTED", "source_file": "blog\\wp-content\\plugins\\bluehost-wordpress-plugin\\vendor\\typesense\\typesense-php\\src\\ApiCall.php", "source_location": "L17", "weight": 1.0}, {"source": "blog_wp_content_plugins_bluehost_wordpress_plugin_vendor_typesense_typesense_php_src_apicall_php", "target": "typesenseclienterror", "relation": "imports", "confidence": "EXTRACTED", "source_file": "blog\\wp-content\\plugins\\bluehost-wordpress-plugin\\vendor\\typesense\\typesense-php\\src\\ApiCall.php", "source_location": "L18", "weight": 1.0}, {"source": "blog_wp_content_plugins_bluehost_wordpress_plugin_vendor_typesense_typesense_php_src_apicall_php", "target": "apicall_apicall", "relation": "contains", "confidence": "EXTRACTED", "source_file": "blog\\wp-content\\plugins\\bluehost-wordpress-plugin\\vendor\\typesense\\typesense-php\\src\\ApiCall.php", "source_location": "L27", "weight": 1.0}, {"source": "apicall_apicall", "target": "apicall_apicall_construct", "relation": "method", "confidence": "EXTRACTED", "source_file": "blog\\wp-content\\plugins\\bluehost-wordpress-plugin\\vendor\\typesense\\typesense-php\\src\\ApiCall.php", "source_location": "L62", "weight": 1.0}, {"source": "apicall_apicall", "target": "apicall_apicall_initializenodes", "relation": "method", "confidence": "EXTRACTED", "source_file": "blog\\wp-content\\plugins\\bluehost-wordpress-plugin\\vendor\\typesense\\typesense-php\\src\\ApiCall.php", "source_location": "L75", "weight": 1.0}, {"source": "apicall_apicall", "target": "apicall_apicall_get", "relation": "method", "confidence": "EXTRACTED", "source_file": "blog\\wp-content\\plugins\\bluehost-wordpress-plugin\\vendor\\typesense\\typesense-php\\src\\ApiCall.php", "source_location": "L95", "weight": 1.0}, {"source": "apicall_apicall", "target": "apicall_apicall_post", "relation": "method", "confidence": "EXTRACTED", "source_file": "blog\\wp-content\\plugins\\bluehost-wordpress-plugin\\vendor\\typesense\\typesense-php\\src\\ApiCall.php", "source_location": "L112", "weight": 1.0}, {"source": "apicall_apicall", "target": "apicall_apicall_put", "relation": "method", "confidence": "EXTRACTED", "source_file": "blog\\wp-content\\plugins\\bluehost-wordpress-plugin\\vendor\\typesense\\typesense-php\\src\\ApiCall.php", "source_location": "L126", "weight": 1.0}, {"source": "apicall_apicall", "target": "apicall_apicall_delete", "relation": "method", "confidence": "EXTRACTED", "source_file": "blog\\wp-content\\plugins\\bluehost-wordpress-plugin\\vendor\\typesense\\typesense-php\\src\\ApiCall.php", "source_location": "L139", "weight": 1.0}, {"source": "apicall_apicall", "target": "apicall_apicall_makerequest", "relation": "method", "confidence": "EXTRACTED", "source_file": "blog\\wp-content\\plugins\\bluehost-wordpress-plugin\\vendor\\typesense\\typesense-php\\src\\ApiCall.php", "source_location": "L156", "weight": 1.0}, {"source": "apicall_apicall", "target": "apicall_apicall_getrequestoptions", "relation": "method", "confidence": "EXTRACTED", "source_file": "blog\\wp-content\\plugins\\bluehost-wordpress-plugin\\vendor\\typesense\\typesense-php\\src\\ApiCall.php", "source_location": "L226", "weight": 1.0}, {"source": "apicall_apicall", "target": "apicall_apicall_nodedueforhealthcheck", "relation": "method", "confidence": "EXTRACTED", "source_file": "blog\\wp-content\\plugins\\bluehost-wordpress-plugin\\vendor\\typesense\\typesense-php\\src\\ApiCall.php", "source_location": "L241", "weight": 1.0}, {"source": "apicall_apicall", "target": "apicall_apicall_setnodehealthcheck", "relation": "method", "confidence": "EXTRACTED", "source_file": "blog\\wp-content\\plugins\\bluehost-wordpress-plugin\\vendor\\typesense\\typesense-php\\src\\ApiCall.php", "source_location": "L256", "weight": 1.0}, {"source": "apicall_apicall", "target": "apicall_apicall_getnode", "relation": "method", "confidence": "EXTRACTED", "source_file": "blog\\wp-content\\plugins\\bluehost-wordpress-plugin\\vendor\\typesense\\typesense-php\\src\\ApiCall.php", "source_location": "L268", "weight": 1.0}, {"source": "apicall_apicall", "target": "apicall_apicall_getexception", "relation": "method", "confidence": "EXTRACTED", "source_file": "blog\\wp-content\\plugins\\bluehost-wordpress-plugin\\vendor\\typesense\\typesense-php\\src\\ApiCall.php", "source_location": "L297", "weight": 1.0}, {"source": "apicall_apicall_construct", "target": "apicall_apicall_initializenodes", "relation": "calls", "confidence": "EXTRACTED", "source_file": "blog\\wp-content\\plugins\\bluehost-wordpress-plugin\\vendor\\typesense\\typesense-php\\src\\ApiCall.php", "source_location": "L69", "weight": 1.0}, {"source": "apicall_apicall_initializenodes", "target": "apicall_apicall_setnodehealthcheck", "relation": "calls", "confidence": "EXTRACTED", "source_file": "blog\\wp-content\\plugins\\bluehost-wordpress-plugin\\vendor\\typesense\\typesense-php\\src\\ApiCall.php", "source_location": "L78", "weight": 1.0}, {"source": "apicall_apicall_get", "target": "apicall_apicall_makerequest", "relation": "calls", "confidence": "EXTRACTED", "source_file": "blog\\wp-content\\plugins\\bluehost-wordpress-plugin\\vendor\\typesense\\typesense-php\\src\\ApiCall.php", "source_location": "L97", "weight": 1.0}, {"source": "apicall_apicall_post", "target": "apicall_apicall_makerequest", "relation": "calls", "confidence": "EXTRACTED", "source_file": "blog\\wp-content\\plugins\\bluehost-wordpress-plugin\\vendor\\typesense\\typesense-php\\src\\ApiCall.php", "source_location": "L114", "weight": 1.0}, {"source": "apicall_apicall_put", "target": "apicall_apicall_makerequest", "relation": "calls", "confidence": "EXTRACTED", "source_file": "blog\\wp-content\\plugins\\bluehost-wordpress-plugin\\vendor\\typesense\\typesense-php\\src\\ApiCall.php", "source_location": "L128", "weight": 1.0}, {"source": "apicall_apicall_delete", "target": "apicall_apicall_makerequest", "relation": "calls", "confidence": "EXTRACTED", "source_file": "blog\\wp-content\\plugins\\bluehost-wordpress-plugin\\vendor\\typesense\\typesense-php\\src\\ApiCall.php", "source_location": "L141", "weight": 1.0}, {"source": "apicall_apicall_makerequest", "target": "apicall_apicall_getnode", "relation": "calls", "confidence": "EXTRACTED", "source_file": "blog\\wp-content\\plugins\\bluehost-wordpress-plugin\\vendor\\typesense\\typesense-php\\src\\ApiCall.php", "source_location": "L162", "weight": 1.0}, {"source": "apicall_apicall_makerequest", "target": "apicall_apicall_getrequestoptions", "relation": "calls", "confidence": "EXTRACTED", "source_file": "blog\\wp-content\\plugins\\bluehost-wordpress-plugin\\vendor\\typesense\\typesense-php\\src\\ApiCall.php", "source_location": "L166", "weight": 1.0}, {"source": "apicall_apicall_makerequest", "target": "apicall_apicall_setnodehealthcheck", "relation": "calls", "confidence": "EXTRACTED", "source_file": "blog\\wp-content\\plugins\\bluehost-wordpress-plugin\\vendor\\typesense\\typesense-php\\src\\ApiCall.php", "source_location": "L181", "weight": 1.0}, {"source": "apicall_apicall_makerequest", "target": "apicall_apicall_getexception", "relation": "calls", "confidence": "EXTRACTED", "source_file": "blog\\wp-content\\plugins\\bluehost-wordpress-plugin\\vendor\\typesense\\typesense-php\\src\\ApiCall.php", "source_location": "L187", "weight": 1.0}, {"source": "apicall_apicall_getnode", "target": "apicall_apicall_nodedueforhealthcheck", "relation": "calls", "confidence": "EXTRACTED", "source_file": "blog\\wp-content\\plugins\\bluehost-wordpress-plugin\\vendor\\typesense\\typesense-php\\src\\ApiCall.php", "source_location": "L271", "weight": 1.0}]}